{"cameraMode":{"drawMode":0,"name":"Shaded","section":"Shading Mode"},"sceneLighting":true,"audioPlay":false,"sceneViewState":{"showFog":true,"showMaterialUpdate":false,"showSkybox":true,"showFlares":true,"showImageEffects":true,"showParticleSystems":true,"showVisualEffectGraphs":true,"m_FxEnabled":true},"in2DMode":false,"pivot":{"x":7.042327880859375,"y":-26.95632553100586,"z":32.93164825439453},"rotation":{"x":-0.3956384062767029,"y":0.07754743099212647,"z":-0.03355541452765465,"w":-0.9144973158836365},"size":50.2215461730957,"orthographic":false}